django_ip_access/__init__.py
django_ip_access/admin.py
django_ip_access/apps.py
django_ip_access/decorators.py
django_ip_access/ip_access_middleware.py
django_ip_access/middleware.py
django_ip_access/mixins.py
django_ip_access/models.py
django_ip_access/responses.py
django_ip_access/tests.py
django_ip_access/utils.py
django_ip_access/migrations/0001_initial.py
django_ip_access/migrations/0002_rename_django_ip_a_ip_add_123456_idx_granted_ips_ip_addr_642e69_idx.py
django_ip_access/migrations/__init__.py
django_ip_access_middleware-1.1.2.dist-info/licenses/LICENSE
django_ip_access_middleware-1.1.2.dist-info/METADATA
django_ip_access_middleware-1.1.2.dist-info/WHEEL
django_ip_access_middleware-1.1.2.dist-info/top_level.txt
django_ip_access_middleware-1.1.2.dist-info/RECORD
