Metadata-Version: 2.4
Name: django-ip-access-middleware
Version: 1.1.2
Summary: Django middleware for IP and hostname-based access control
Home-page: https://github.com/mhmohamad1380/django-ip-access-middleware
Author: Mohammad Mohammad Hosseini
Author-email: Mohammad Mohammad Hosseini <dev.mohamadhosseiny@gmail.com>
License: MIT
Project-URL: Homepage, https://github.com/mhmohamad1380/django-ip-access-middleware
Project-URL: Documentation, https://mhmohamad1380.github.io/django-ip-access-middleware
Project-URL: Repository, https://github.com/mhmohamad1380/django-ip-access-middleware
Keywords: django,middleware,ip,access,control,hostname,kubernetes,security
Classifier: Development Status :: 4 - Beta
Classifier: Environment :: Web Environment
Classifier: Framework :: Django
Classifier: Framework :: Django :: 3.2
Classifier: Framework :: Django :: 4.0
Classifier: Framework :: Django :: 4.1
Classifier: Framework :: Django :: 4.2
Classifier: Framework :: Django :: 5.0
Classifier: Framework :: Django :: 5.1
Classifier: Framework :: Django :: 5.2
Classifier: Intended Audience :: Developers
Classifier: License :: OSI Approved :: MIT License
Classifier: Operating System :: OS Independent
Classifier: Programming Language :: Python
Classifier: Programming Language :: Python :: 3
Classifier: Programming Language :: Python :: 3.8
Classifier: Programming Language :: Python :: 3.9
Classifier: Programming Language :: Python :: 3.10
Classifier: Programming Language :: Python :: 3.11
Classifier: Programming Language :: Python :: 3.12
Classifier: Topic :: Internet :: WWW/HTTP
Classifier: Topic :: Internet :: WWW/HTTP :: WSGI :: Middleware
Classifier: Topic :: Security
Requires-Python: >=3.8
License-File: LICENSE
Requires-Dist: Django>=3.2
Provides-Extra: dev
Requires-Dist: netifaces>=0.11.0; extra == "dev"
Dynamic: author
Dynamic: home-page
Dynamic: license-file
Dynamic: requires-python
